quetzal_openapi_client-0.5.0-py3.7-nspkg.pth
quetzal/openapi_client/__init__.py
quetzal/openapi_client/api_client.py
quetzal/openapi_client/configuration.py
quetzal/openapi_client/rest.py
quetzal/openapi_client/api/__init__.py
quetzal/openapi_client/api/authentication_api.py
quetzal/openapi_client/api/data_api.py
quetzal/openapi_client/api/public_api.py
quetzal/openapi_client/api/query_api.py
quetzal/openapi_client/api/workspace_api.py
quetzal/openapi_client/models/__init__.py
quetzal/openapi_client/models/base_metadata.py
quetzal/openapi_client/models/error.py
quetzal/openapi_client/models/file_contents.py
quetzal/openapi_client/models/metadata_by_family.py
quetzal/openapi_client/models/paginated_files.py
quetzal/openapi_client/models/paginated_queries.py
quetzal/openapi_client/models/paginated_workspaces.py
quetzal/openapi_client/models/pagination_envelope.py
quetzal/openapi_client/models/query.py
quetzal/openapi_client/models/query_no_results.py
quetzal/openapi_client/models/token.py
quetzal/openapi_client/models/workspace.py
test/__init__.py
test/test_authentication_api.py
test/test_base_metadata.py
test/test_data_api.py
test/test_error.py
test/test_file_contents.py
test/test_metadata_by_family.py
test/test_paginated_files.py
test/test_paginated_queries.py
test/test_paginated_workspaces.py
test/test_pagination_envelope.py
test/test_public_api.py
test/test_query.py
test/test_query_api.py
test/test_query_no_results.py
test/test_token.py
test/test_workspace.py
test/test_workspace_api.py
quetzal_openapi_client-0.5.0.dist-info/LICENSE
quetzal_openapi_client-0.5.0.dist-info/METADATA
quetzal_openapi_client-0.5.0.dist-info/WHEEL
quetzal_openapi_client-0.5.0.dist-info/namespace_packages.txt
quetzal_openapi_client-0.5.0.dist-info/top_level.txt
quetzal_openapi_client-0.5.0.dist-info/RECORD
