Metadata-Version: 2.1
Name: quetzal-openapi-client
Version: 0.5.0
Summary: Quetzal API auto-generated client
Home-page: https://github.com/quet.zal/quetzal-openapi-client
Author: David Ojeda
Author-email: support@quetz.al
License: BSD-3-Clause
Project-URL: Documentation, https://quetzal-openapi-client.readthedocs.io
Project-URL: Code, https://github.com/quetz-al/quetzal-openapi-client
Project-URL: Issue tracker, https://github.com/quetz-al/quetzal-openapi-client/issues
Keywords: OpenAPI,OpenAPI-Generator,Quetzal API
Platform: UNKNOWN
Classifier: Development Status :: 4 - Beta
Classifier: Intended Audience :: Developers
Classifier: License :: OSI Approved :: BSD License
Classifier: Operating System :: OS Independent
Classifier: Programming Language :: Python :: 2.7
Classifier: Programming Language :: Python :: 3.6
Classifier: Programming Language :: Python :: 3.7
Classifier: Programming Language :: Python :: 3.8
Classifier: Topic :: Database :: Front-Ends
Classifier: Topic :: Internet :: WWW/HTTP
Classifier: Topic :: System :: Archiving
Requires-Dist: urllib3 (>=1.15)
Requires-Dist: six (>=1.10)
Requires-Dist: certifi
Requires-Dist: python-dateutil
